interleave/__init__.py
interleave/py.typed
interleave-0.2.2.dist-info/METADATA
interleave-0.2.2.dist-info/WHEEL
interleave-0.2.2.dist-info/licenses/LICENSE
interleave-0.2.2.dist-info/RECORD
