Metadata-Version: 2.3
Name: interleave
Version: 0.2.2
Summary: Yield from multiple iterators as values become available
Project-URL: Source Code, https://github.com/jwodder/interleave
Project-URL: Bug Tracker, https://github.com/jwodder/interleave/issues
Author-email: John Thorvald Wodder II <interleave@varonathe.org>
License: MIT
Keywords: interleaving,iterators,multithreading
Classifier: Intended Audience :: Developers
Classifier: License :: OSI Approved :: MIT License
Classifier: Programming Language :: Python :: 3
Classifier: Programming Language :: Python :: 3 :: Only
Classifier: Programming Language :: Python :: 3.8
Classifier: Programming Language :: Python :: 3.9
Classifier: Programming Language :: Python :: 3.10
Classifier: Programming Language :: Python :: 3.11
Classifier: Programming Language :: Python :: 3.12
Classifier: Programming Language :: Python :: 3.13
Classifier: Programming Language :: Python :: Implementation :: CPython
Classifier: Programming Language :: Python :: Implementation :: PyPy
Classifier: Topic :: Utilities
Classifier: Typing :: Typed
Requires-Python: >=3.8
